mykeepin/__init__.py
mykeepin/constans.py
mykeepin/exceptions.py
mykeepin/tests.py
mykeepin/utils.py
mykeepin/crypto/__init__.py
mykeepin/crypto/signature.py
mykeepin/did/__init__.py
mykeepin/did/document.py
mykeepin/did/resolver.py
mykeepin/did/verifier.py
mykeepin/verifiable/__init__.py
mykeepin/verifiable/credential.py
mykeepin/verifiable/encryption.py
mykeepin/verifiable/presentation.py
mykeepin/verifiable/sign.py
mykeepin_sdk-0.2.0.dist-info/LICENSE
mykeepin_sdk-0.2.0.dist-info/METADATA
mykeepin_sdk-0.2.0.dist-info/WHEEL
mykeepin_sdk-0.2.0.dist-info/top_level.txt
mykeepin_sdk-0.2.0.dist-info/RECORD
