Metadata-Version: 2.1
Name: mykeepin-sdk
Version: 0.2.0
Summary: MyKeepin SDK for python
Home-page: https://github.com/coinplug/mykeepin-sdk-py
Maintainer: Coinplug, Inc.
Maintainer-email: inyong@coinplug.com
License: LGPLv3+
Platform: UNKNOWN
Classifier: Programming Language :: Python :: 3
Classifier: License :: OSI Approved :: GNU Lesser General Public License v3 (LGPLv3)
Requires-Python: >=3.7
Requires-Dist: web3
Requires-Dist: ecdsa
Requires-Dist: requests
Requires-Dist: jwcrypto
